{
  "id" : "newForm2",
  "name" : "newForm2",
  "type" : "form",
  "uuid" : "d4b12b26-b273-4133-beff-9dfe6118d43d",
  "modelVersion" : "2.6",
  "lastUpdate" : 1744561974180,
  "description" : "Page generated with Bonita UI designer",
  "rows" : [
    [
      {
        "type" : "container",
        "dimension" : {
          "xs" : 12
        },
        "propertyValues" : { },
        "reference" : "4803e1c8-6367-470e-87b3-3ef5824c8fa4",
        "hasValidationError" : false,
        "id" : "pbContainer",
        "rows" : [
          [
            {
              "type" : "component",
              "dimension" : {
                "md" : 12,
                "sm" : 12,
                "xs" : 12,
                "lg" : 12
              },
              "propertyValues" : {
                "hidden" : {
                  "type" : "constant",
                  "value" : false
                },
                "level" : {
                  "type" : "constant",
                  "value" : "Level 1"
                },
                "cssClasses" : {
                  "type" : "constant",
                  "value" : ""
                },
                "text" : {
                  "type" : "interpolation",
                  "value" : "{{ task.displayName }}"
                },
                "alignment" : {
                  "type" : "constant",
                  "value" : "center"
                },
                "dimension" : {
                  "type" : "constant",
                  "value" : 12
                }
              },
              "reference" : "31332e94-60d0-4347-ba49-363f103462d3",
              "hasValidationError" : false,
              "id" : "pbTitle",
              "description" : ""
            }
          ],
          [
            {
              "type" : "component",
              "dimension" : {
                "md" : 12,
                "sm" : 12,
                "xs" : 12,
                "lg" : 12
              },
              "propertyValues" : {
                "allowHtml" : {
                  "type" : "constant",
                  "value" : true
                },
                "labelHidden" : {
                  "type" : "constant",
                  "value" : true
                },
                "hidden" : {
                  "type" : "constant",
                  "value" : false
                },
                "cssClasses" : {
                  "type" : "constant",
                  "value" : ""
                },
                "label" : {
                  "type" : "interpolation"
                },
                "text" : {
                  "type" : "interpolation",
                  "value" : "{{ task.displayDescription }}"
                },
                "alignment" : {
                  "type" : "constant",
                  "value" : "left"
                },
                "dimension" : {
                  "type" : "constant",
                  "value" : 12
                }
              },
              "reference" : "ceb7880d-992f-4d2b-9c64-adcf7e552d47",
              "hasValidationError" : false,
              "id" : "pbText",
              "description" : ""
            }
          ]
        ]
      }
    ],
    [
      {
        "type" : "formContainer",
        "dimension" : {
          "xs" : 12
        },
        "propertyValues" : { },
        "reference" : "43f31d88-5e07-488d-83fc-527c17c4770c",
        "hasValidationError" : false,
        "id" : "pbFormContainer",
        "container" : {
          "type" : "container",
          "dimension" : {
            "xs" : 12
          },
          "propertyValues" : { },
          "reference" : "97baaaf6-fda6-460b-8702-ec5354b2b22c",
          "hasValidationError" : false,
          "id" : "pbContainer",
          "rows" : [
            [
              {
                "type" : "component",
                "dimension" : {
                  "md" : 12,
                  "sm" : 12,
                  "xs" : 12,
                  "lg" : 12
                },
                "propertyValues" : {
                  "hidden" : {
                    "type" : "constant",
                    "value" : false
                  },
                  "level" : {
                    "type" : "constant",
                    "value" : "Level 4"
                  },
                  "cssClasses" : {
                    "type" : "constant",
                    "value" : ""
                  },
                  "text" : {
                    "type" : "interpolation",
                    "value" : "Slipstream"
                  },
                  "alignment" : {
                    "type" : "constant",
                    "value" : "left"
                  },
                  "dimension" : {
                    "type" : "constant",
                    "value" : 12
                  }
                },
                "reference" : "54f82147-3e85-49ce-a326-8c42f0f03356",
                "hasValidationError" : false,
                "id" : "pbTitle",
                "description" : ""
              }
            ],
            [
              {
                "type" : "container",
                "dimension" : {
                  "md" : 12,
                  "sm" : 12,
                  "xs" : 12,
                  "lg" : 12
                },
                "propertyValues" : {
                  "repeatedCollection" : {
                    "type" : "variable"
                  },
                  "hidden" : {
                    "type" : "constant",
                    "value" : false
                  },
                  "cssClasses" : {
                    "type" : "constant",
                    "value" : ""
                  },
                  "dimension" : {
                    "type" : "constant",
                    "value" : 12
                  }
                },
                "reference" : "f0349c32-de9e-4224-9081-d1cd3721cdd5",
                "hasValidationError" : false,
                "id" : "pbContainer",
                "rows" : [
                  [
                    {
                      "type" : "component",
                      "dimension" : {
                        "md" : 12,
                        "sm" : 12,
                        "xs" : 12,
                        "lg" : 12
                      },
                      "propertyValues" : {
                        "labelHidden" : {
                          "type" : "constant",
                          "value" : false
                        },
                        "hidden" : {
                          "type" : "constant",
                          "value" : false
                        },
                        "labelPosition" : {
                          "type" : "constant",
                          "value" : "top"
                        },
                        "cssClasses" : {
                          "type" : "constant",
                          "value" : ""
                        },
                        "labelWidth" : {
                          "type" : "constant",
                          "value" : 1
                        },
                        "readOnly" : {
                          "type" : "constant",
                          "value" : false
                        },
                        "label" : {
                          "type" : "interpolation",
                          "value" : "Client_name"
                        },
                        "placeholder" : {
                          "type" : "constant"
                        },
                        "type" : {
                          "type" : "constant",
                          "value" : "text"
                        },
                        "dimension" : {
                          "type" : "constant",
                          "value" : 12
                        },
                        "value" : {
                          "type" : "variable",
                          "value" : "slipstream.client_name"
                        },
                        "required" : {
                          "type" : "constant",
                          "value" : false
                        }
                      },
                      "reference" : "001a7556-1561-40c1-bfbe-b8dfa639c11b",
                      "hasValidationError" : false,
                      "id" : "pbInput",
                      "description" : ""
                    }
                  ],
                  [
                    {
                      "type" : "component",
                      "dimension" : {
                        "md" : 12,
                        "sm" : 12,
                        "xs" : 12,
                        "lg" : 12
                      },
                      "propertyValues" : {
                        "labelHidden" : {
                          "type" : "constant",
                          "value" : false
                        },
                        "hidden" : {
                          "type" : "constant",
                          "value" : false
                        },
                        "labelPosition" : {
                          "type" : "constant",
                          "value" : "top"
                        },
                        "cssClasses" : {
                          "type" : "constant",
                          "value" : ""
                        },
                        "labelWidth" : {
                          "type" : "constant",
                          "value" : 1
                        },
                        "readOnly" : {
                          "type" : "constant",
                          "value" : false
                        },
                        "label" : {
                          "type" : "interpolation",
                          "value" : "Client_ I D"
                        },
                        "placeholder" : {
                          "type" : "constant"
                        },
                        "type" : {
                          "type" : "constant",
                          "value" : "number"
                        },
                        "dimension" : {
                          "type" : "constant",
                          "value" : 12
                        },
                        "value" : {
                          "type" : "variable",
                          "value" : "slipstream.client_ID"
                        },
                        "required" : {
                          "type" : "constant",
                          "value" : false
                        }
                      },
                      "reference" : "60d54dcf-c629-41e0-8a7b-29b532da4540",
                      "hasValidationError" : false,
                      "id" : "pbInput",
                      "description" : ""
                    }
                  ],
                  [
                    {
                      "type" : "component",
                      "dimension" : {
                        "md" : 12,
                        "sm" : 12,
                        "xs" : 12,
                        "lg" : 12
                      },
                      "propertyValues" : {
                        "labelHidden" : {
                          "type" : "constant",
                          "value" : false
                        },
                        "hidden" : {
                          "type" : "constant",
                          "value" : false
                        },
                        "cssClasses" : {
                          "type" : "constant",
                          "value" : ""
                        },
                        "disabled" : {
                          "type" : "constant",
                          "value" : false
                        },
                        "label" : {
                          "type" : "interpolation",
                          "value" : "Hin_exist"
                        },
                        "dimension" : {
                          "type" : "constant",
                          "value" : 12
                        },
                        "value" : {
                          "type" : "variable",
                          "value" : "slipstream.hin_exist"
                        }
                      },
                      "reference" : "9479ccee-1b05-45b4-86f0-25b61e3b0916",
                      "hasValidationError" : false,
                      "id" : "pbCheckbox",
                      "description" : ""
                    }
                  ],
                  [
                    {
                      "type" : "component",
                      "dimension" : {
                        "md" : 12,
                        "sm" : 12,
                        "xs" : 12,
                        "lg" : 12
                      },
                      "propertyValues" : {
                        "labelHidden" : {
                          "type" : "constant",
                          "value" : false
                        },
                        "hidden" : {
                          "type" : "constant",
                          "value" : false
                        },
                        "labelPosition" : {
                          "type" : "constant",
                          "value" : "top"
                        },
                        "cssClasses" : {
                          "type" : "constant",
                          "value" : ""
                        },
                        "labelWidth" : {
                          "type" : "constant",
                          "value" : 1
                        },
                        "readOnly" : {
                          "type" : "constant",
                          "value" : false
                        },
                        "label" : {
                          "type" : "interpolation",
                          "value" : "Hin_number"
                        },
                        "placeholder" : {
                          "type" : "constant"
                        },
                        "type" : {
                          "type" : "constant",
                          "value" : "text"
                        },
                        "dimension" : {
                          "type" : "constant",
                          "value" : 12
                        },
                        "value" : {
                          "type" : "variable",
                          "value" : "slipstream.hin_number"
                        },
                        "required" : {
                          "type" : "constant",
                          "value" : false
                        }
                      },
                      "reference" : "4b9c8a48-0925-4c5f-8fad-7e7dbb8683be",
                      "hasValidationError" : false,
                      "id" : "pbInput",
                      "description" : ""
                    }
                  ],
                  [
                    {
                      "type" : "component",
                      "dimension" : {
                        "md" : 12,
                        "sm" : 12,
                        "xs" : 12,
                        "lg" : 12
                      },
                      "propertyValues" : {
                        "labelHidden" : {
                          "type" : "constant",
                          "value" : false
                        },
                        "hidden" : {
                          "type" : "constant",
                          "value" : false
                        },
                        "labelPosition" : {
                          "type" : "constant",
                          "value" : "top"
                        },
                        "cssClasses" : {
                          "type" : "constant",
                          "value" : ""
                        },
                        "labelWidth" : {
                          "type" : "constant",
                          "value" : 1
                        },
                        "readOnly" : {
                          "type" : "constant",
                          "value" : false
                        },
                        "label" : {
                          "type" : "interpolation",
                          "value" : "Daily_transaction_limit"
                        },
                        "placeholder" : {
                          "type" : "constant"
                        },
                        "type" : {
                          "type" : "constant",
                          "value" : "number"
                        },
                        "dimension" : {
                          "type" : "constant",
                          "value" : 12
                        },
                        "value" : {
                          "type" : "variable",
                          "value" : "slipstream.daily_transaction_limit"
                        },
                        "required" : {
                          "type" : "constant",
                          "value" : false
                        }
                      },
                      "reference" : "55413d71-eae1-4db6-a92b-b9067ec4fbff",
                      "hasValidationError" : false,
                      "id" : "pbInput",
                      "description" : ""
                    }
                  ],
                  [
                    {
                      "type" : "component",
                      "dimension" : {
                        "md" : 12,
                        "sm" : 12,
                        "xs" : 12,
                        "lg" : 12
                      },
                      "propertyValues" : {
                        "labelHidden" : {
                          "type" : "constant",
                          "value" : false
                        },
                        "hidden" : {
                          "type" : "constant",
                          "value" : false
                        },
                        "cssClasses" : {
                          "type" : "constant",
                          "value" : ""
                        },
                        "disabled" : {
                          "type" : "constant",
                          "value" : false
                        },
                        "label" : {
                          "type" : "interpolation",
                          "value" : "Asset_transfer_requested"
                        },
                        "dimension" : {
                          "type" : "constant",
                          "value" : 12
                        },
                        "value" : {
                          "type" : "variable",
                          "value" : "slipstream.asset_transfer_requested"
                        }
                      },
                      "reference" : "f0f34dda-5ac3-4839-aab6-ea35e2c61051",
                      "hasValidationError" : false,
                      "id" : "pbCheckbox",
                      "description" : ""
                    }
                  ],
                  [
                    {
                      "type" : "component",
                      "dimension" : {
                        "md" : 12,
                        "sm" : 12,
                        "xs" : 12,
                        "lg" : 12
                      },
                      "propertyValues" : {
                        "labelHidden" : {
                          "type" : "constant",
                          "value" : false
                        },
                        "hidden" : {
                          "type" : "constant",
                          "value" : false
                        },
                        "labelPosition" : {
                          "type" : "constant",
                          "value" : "top"
                        },
                        "cssClasses" : {
                          "type" : "constant",
                          "value" : ""
                        },
                        "labelWidth" : {
                          "type" : "constant",
                          "value" : 1
                        },
                        "readOnly" : {
                          "type" : "constant",
                          "value" : false
                        },
                        "label" : {
                          "type" : "interpolation",
                          "value" : "Client_existing_broker"
                        },
                        "placeholder" : {
                          "type" : "constant"
                        },
                        "type" : {
                          "type" : "constant",
                          "value" : "text"
                        },
                        "dimension" : {
                          "type" : "constant",
                          "value" : 12
                        },
                        "value" : {
                          "type" : "variable",
                          "value" : "slipstream.client_existing_broker"
                        },
                        "required" : {
                          "type" : "constant",
                          "value" : false
                        }
                      },
                      "reference" : "a6d21cf8-a05e-4259-868e-942ef6fa67dd",
                      "hasValidationError" : false,
                      "id" : "pbInput",
                      "description" : ""
                    }
                  ],
                  [
                    {
                      "type" : "component",
                      "dimension" : {
                        "md" : 12,
                        "sm" : 12,
                        "xs" : 12,
                        "lg" : 12
                      },
                      "propertyValues" : {
                        "labelHidden" : {
                          "type" : "constant",
                          "value" : false
                        },
                        "hidden" : {
                          "type" : "constant",
                          "value" : false
                        },
                        "labelPosition" : {
                          "type" : "constant",
                          "value" : "top"
                        },
                        "cssClasses" : {
                          "type" : "constant",
                          "value" : ""
                        },
                        "labelWidth" : {
                          "type" : "constant",
                          "value" : 1
                        },
                        "readOnly" : {
                          "type" : "constant",
                          "value" : false
                        },
                        "label" : {
                          "type" : "interpolation",
                          "value" : "Current_cash"
                        },
                        "placeholder" : {
                          "type" : "constant"
                        },
                        "type" : {
                          "type" : "constant",
                          "value" : "number"
                        },
                        "dimension" : {
                          "type" : "constant",
                          "value" : 12
                        },
                        "value" : {
                          "type" : "variable",
                          "value" : "slipstream.current_cash"
                        },
                        "required" : {
                          "type" : "constant",
                          "value" : false
                        }
                      },
                      "reference" : "b701e70b-a725-47d3-9aa2-3a8d6d0edfcf",
                      "hasValidationError" : false,
                      "id" : "pbInput",
                      "description" : ""
                    }
                  ],
                  [
                    {
                      "type" : "component",
                      "dimension" : {
                        "md" : 12,
                        "sm" : 12,
                        "xs" : 12,
                        "lg" : 12
                      },
                      "propertyValues" : {
                        "labelHidden" : {
                          "type" : "constant",
                          "value" : false
                        },
                        "hidden" : {
                          "type" : "constant",
                          "value" : false
                        },
                        "labelPosition" : {
                          "type" : "constant",
                          "value" : "top"
                        },
                        "cssClasses" : {
                          "type" : "constant",
                          "value" : ""
                        },
                        "labelWidth" : {
                          "type" : "constant",
                          "value" : 1
                        },
                        "readOnly" : {
                          "type" : "constant",
                          "value" : false
                        },
                        "label" : {
                          "type" : "interpolation",
                          "value" : "Broker_ I D"
                        },
                        "placeholder" : {
                          "type" : "constant"
                        },
                        "type" : {
                          "type" : "constant",
                          "value" : "number"
                        },
                        "dimension" : {
                          "type" : "constant",
                          "value" : 12
                        },
                        "value" : {
                          "type" : "variable",
                          "value" : "slipstream.broker_ID"
                        },
                        "required" : {
                          "type" : "constant",
                          "value" : false
                        }
                      },
                      "reference" : "7794cf0b-343f-4d19-962d-b3e61a1c1da1",
                      "hasValidationError" : false,
                      "id" : "pbInput",
                      "description" : ""
                    }
                  ],
                  [
                    {
                      "type" : "component",
                      "dimension" : {
                        "md" : 12,
                        "sm" : 12,
                        "xs" : 12,
                        "lg" : 12
                      },
                      "propertyValues" : {
                        "labelHidden" : {
                          "type" : "constant",
                          "value" : false
                        },
                        "hidden" : {
                          "type" : "constant",
                          "value" : false
                        },
                        "cssClasses" : {
                          "type" : "constant",
                          "value" : ""
                        },
                        "disabled" : {
                          "type" : "constant",
                          "value" : false
                        },
                        "label" : {
                          "type" : "interpolation",
                          "value" : "Trading_status"
                        },
                        "dimension" : {
                          "type" : "constant",
                          "value" : 12
                        },
                        "value" : {
                          "type" : "variable",
                          "value" : "slipstream.trading_status"
                        }
                      },
                      "reference" : "51d8fe03-5d45-43ba-b5da-86cd3068d3c5",
                      "hasValidationError" : false,
                      "id" : "pbCheckbox",
                      "description" : ""
                    }
                  ],
                  [
                    {
                      "type" : "component",
                      "dimension" : {
                        "md" : 12,
                        "sm" : 12,
                        "xs" : 12,
                        "lg" : 12
                      },
                      "propertyValues" : {
                        "hidden" : {
                          "type" : "constant",
                          "value" : false
                        },
                        "level" : {
                          "type" : "constant",
                          "value" : "Level 4"
                        },
                        "cssClasses" : {
                          "type" : "constant",
                          "value" : ""
                        },
                        "text" : {
                          "type" : "interpolation",
                          "value" : "Account_information"
                        },
                        "alignment" : {
                          "type" : "constant",
                          "value" : "left"
                        },
                        "dimension" : {
                          "type" : "constant",
                          "value" : 12
                        }
                      },
                      "reference" : "62df83c1-f262-4e96-8c83-995d0f6f1a34",
                      "hasValidationError" : false,
                      "id" : "pbTitle",
                      "description" : ""
                    }
                  ],
                  [
                    {
                      "type" : "container",
                      "dimension" : {
                        "md" : 12,
                        "sm" : 12,
                        "xs" : 12,
                        "lg" : 12
                      },
                      "propertyValues" : {
                        "repeatedCollection" : {
                          "type" : "variable",
                          "value" : "slipstream_account_information"
                        },
                        "hidden" : {
                          "type" : "constant",
                          "value" : false
                        },
                        "cssClasses" : {
                          "type" : "constant",
                          "value" : ""
                        },
                        "dimension" : {
                          "type" : "constant",
                          "value" : 12
                        }
                      },
                      "reference" : "77cdae44-f022-47c3-8c94-d56ef91c2a9a",
                      "hasValidationError" : false,
                      "id" : "pbContainer",
                      "rows" : [
                        [
                          {
                            "type" : "component",
                            "dimension" : {
                              "md" : 12,
                              "sm" : 12,
                              "xs" : 12,
                              "lg" : 12
                            },
                            "propertyValues" : {
                              "labelHidden" : {
                                "type" : "constant",
                                "value" : false
                              },
                              "hidden" : {
                                "type" : "constant",
                                "value" : false
                              },
                              "labelPosition" : {
                                "type" : "constant",
                                "value" : "top"
                              },
                              "cssClasses" : {
                                "type" : "constant",
                                "value" : ""
                              },
                              "availableValues" : {
                                "type" : "expression",
                                "value" : "accountInformation_query"
                              },
                              "labelWidth" : {
                                "type" : "constant",
                                "value" : 1
                              },
                              "label" : {
                                "type" : "interpolation",
                                "value" : "Account_information"
                              },
                              "placeholder" : {
                                "type" : "constant",
                                "value" : "Select a Account_information"
                              },
                              "dimension" : {
                                "type" : "constant",
                                "value" : 12
                              },
                              "value" : {
                                "type" : "variable",
                                "value" : "$item"
                              },
                              "required" : {
                                "type" : "constant",
                                "value" : true
                              }
                            },
                            "reference" : "7b244118-b461-42c5-aa49-6a75ae5331a1",
                            "hasValidationError" : false,
                            "id" : "pbSelect",
                            "description" : ""
                          }
                        ],
                        [
                          {
                            "type" : "component",
                            "dimension" : {
                              "md" : 12,
                              "sm" : 12,
                              "xs" : 12,
                              "lg" : 12
                            },
                            "propertyValues" : {
                              "allowHtml" : {
                                "type" : "constant",
                                "value" : true
                              },
                              "labelHidden" : {
                                "type" : "constant",
                                "value" : false
                              },
                              "hidden" : {
                                "type" : "expression",
                                "value" : "!$item.account_username"
                              },
                              "cssClasses" : {
                                "type" : "constant",
                                "value" : ""
                              },
                              "label" : {
                                "type" : "interpolation",
                                "value" : "Account_username"
                              },
                              "text" : {
                                "type" : "interpolation",
                                "value" : "{{$item.account_username}}"
                              },
                              "alignment" : {
                                "type" : "constant",
                                "value" : "left"
                              },
                              "dimension" : {
                                "type" : "constant",
                                "value" : 12
                              }
                            },
                            "reference" : "4dc747be-0f21-47e0-b786-7abb6e79d330",
                            "hasValidationError" : false,
                            "id" : "pbText",
                            "description" : ""
                          }
                        ],
                        [
                          {
                            "type" : "component",
                            "dimension" : {
                              "md" : 12,
                              "sm" : 12,
                              "xs" : 12,
                              "lg" : 12
                            },
                            "propertyValues" : {
                              "allowHtml" : {
                                "type" : "constant",
                                "value" : true
                              },
                              "labelHidden" : {
                                "type" : "constant",
                                "value" : false
                              },
                              "hidden" : {
                                "type" : "expression",
                                "value" : "!$item.account_password"
                              },
                              "cssClasses" : {
                                "type" : "constant",
                                "value" : ""
                              },
                              "label" : {
                                "type" : "interpolation",
                                "value" : "Account_password"
                              },
                              "text" : {
                                "type" : "interpolation",
                                "value" : "{{$item.account_password}}"
                              },
                              "alignment" : {
                                "type" : "constant",
                                "value" : "left"
                              },
                              "dimension" : {
                                "type" : "constant",
                                "value" : 12
                              }
                            },
                            "reference" : "5d34f983-e959-467b-b45b-0adb2c6d7ca9",
                            "hasValidationError" : false,
                            "id" : "pbText",
                            "description" : ""
                          }
                        ],
                        [
                          {
                            "type" : "component",
                            "dimension" : {
                              "md" : 12,
                              "sm" : 12,
                              "xs" : 12,
                              "lg" : 12
                            },
                            "propertyValues" : {
                              "allowHtml" : {
                                "type" : "constant",
                                "value" : true
                              },
                              "labelHidden" : {
                                "type" : "constant",
                                "value" : false
                              },
                              "hidden" : {
                                "type" : "expression",
                                "value" : "!$item.account_creationDate"
                              },
                              "cssClasses" : {
                                "type" : "constant",
                                "value" : ""
                              },
                              "label" : {
                                "type" : "interpolation",
                                "value" : "Account_creation Date"
                              },
                              "text" : {
                                "type" : "interpolation",
                                "value" : "{{$item.account_creationDate|uiDate}}"
                              },
                              "alignment" : {
                                "type" : "constant",
                                "value" : "left"
                              },
                              "dimension" : {
                                "type" : "constant",
                                "value" : 12
                              }
                            },
                            "reference" : "fa0280c8-fc37-43f7-ac99-6d80f5dfca51",
                            "hasValidationError" : false,
                            "id" : "pbText",
                            "description" : ""
                          }
                        ],
                        [
                          {
                            "type" : "component",
                            "dimension" : {
                              "md" : 12,
                              "sm" : 12,
                              "xs" : 12,
                              "lg" : 12
                            },
                            "propertyValues" : {
                              "allowHtml" : {
                                "type" : "constant",
                                "value" : true
                              },
                              "labelHidden" : {
                                "type" : "constant",
                                "value" : false
                              },
                              "hidden" : {
                                "type" : "expression",
                                "value" : "!$item.account_clientID"
                              },
                              "cssClasses" : {
                                "type" : "constant",
                                "value" : ""
                              },
                              "label" : {
                                "type" : "interpolation",
                                "value" : "Account_client I D"
                              },
                              "text" : {
                                "type" : "interpolation",
                                "value" : "{{$item.account_clientID}}"
                              },
                              "alignment" : {
                                "type" : "constant",
                                "value" : "left"
                              },
                              "dimension" : {
                                "type" : "constant",
                                "value" : 12
                              }
                            },
                            "reference" : "af100187-47df-4b38-b370-bf9a0dc2ea2c",
                            "hasValidationError" : false,
                            "id" : "pbText",
                            "description" : ""
                          }
                        ],
                        [
                          {
                            "type" : "component",
                            "dimension" : {
                              "md" : 12,
                              "sm" : 12,
                              "xs" : 12,
                              "lg" : 12
                            },
                            "propertyValues" : {
                              "allowHtml" : {
                                "type" : "constant",
                                "value" : true
                              },
                              "labelHidden" : {
                                "type" : "constant",
                                "value" : false
                              },
                              "hidden" : {
                                "type" : "expression",
                                "value" : "!$item.account_clientname"
                              },
                              "cssClasses" : {
                                "type" : "constant",
                                "value" : ""
                              },
                              "label" : {
                                "type" : "interpolation",
                                "value" : "Account_clientname"
                              },
                              "text" : {
                                "type" : "interpolation",
                                "value" : "{{$item.account_clientname}}"
                              },
                              "alignment" : {
                                "type" : "constant",
                                "value" : "left"
                              },
                              "dimension" : {
                                "type" : "constant",
                                "value" : 12
                              }
                            },
                            "reference" : "8f1b00e0-6f56-4713-80f1-f352b5e87da7",
                            "hasValidationError" : false,
                            "id" : "pbText",
                            "description" : ""
                          }
                        ],
                        [
                          {
                            "type" : "component",
                            "dimension" : {
                              "md" : 12,
                              "sm" : 12,
                              "xs" : 12,
                              "lg" : 12
                            },
                            "propertyValues" : {
                              "removeItem" : {
                                "type" : "variable",
                                "value" : "$item"
                              },
                              "hidden" : {
                                "type" : "constant",
                                "value" : false
                              },
                              "cssClasses" : {
                                "type" : "constant",
                                "value" : ""
                              },
                              "buttonStyle" : {
                                "type" : "constant",
                                "value" : "danger"
                              },
                              "label" : {
                                "type" : "interpolation",
                                "value" : "<span class=\"glyphicon glyphicon-remove\"></span>"
                              },
                              "dataToSend" : {
                                "type" : "expression"
                              },
                              "allowHTML" : {
                                "type" : "constant",
                                "value" : true
                              },
                              "labelHidden" : {
                                "type" : "constant",
                                "value" : false
                              },
                              "collectionPosition" : {
                                "type" : "constant",
                                "value" : "Item"
                              },
                              "targetUrlOnSuccess" : {
                                "type" : "interpolation"
                              },
                              "action" : {
                                "type" : "constant",
                                "value" : "Remove from collection"
                              },
                              "collectionToModify" : {
                                "type" : "variable",
                                "value" : "$collection"
                              },
                              "valueToAdd" : {
                                "type" : "expression"
                              },
                              "disabled" : {
                                "type" : "constant",
                                "value" : false
                              },
                              "alignment" : {
                                "type" : "constant",
                                "value" : "right"
                              },
                              "dimension" : {
                                "type" : "constant",
                                "value" : 12
                              }
                            },
                            "reference" : "4b6d5782-2596-478e-a42e-a86f18a2c0a4",
                            "hasValidationError" : false,
                            "id" : "pbButton",
                            "description" : ""
                          }
                        ]
                      ]
                    }
                  ],
                  [
                    {
                      "type" : "component",
                      "dimension" : {
                        "md" : 12,
                        "sm" : 12,
                        "xs" : 12,
                        "lg" : 12
                      },
                      "propertyValues" : {
                        "removeItem" : {
                          "type" : "variable"
                        },
                        "hidden" : {
                          "type" : "constant",
                          "value" : false
                        },
                        "cssClasses" : {
                          "type" : "constant",
                          "value" : ""
                        },
                        "buttonStyle" : {
                          "type" : "constant",
                          "value" : "primary"
                        },
                        "label" : {
                          "type" : "interpolation",
                          "value" : "<span class=\"glyphicon glyphicon-plus\"></span> Add AccountInformation"
                        },
                        "dataToSend" : {
                          "type" : "expression"
                        },
                        "allowHTML" : {
                          "type" : "constant",
                          "value" : true
                        },
                        "labelHidden" : {
                          "type" : "constant",
                          "value" : false
                        },
                        "collectionPosition" : {
                          "type" : "constant"
                        },
                        "targetUrlOnSuccess" : {
                          "type" : "interpolation"
                        },
                        "action" : {
                          "type" : "constant",
                          "value" : "Add to collection"
                        },
                        "collectionToModify" : {
                          "type" : "variable",
                          "value" : "slipstream_account_information"
                        },
                        "valueToAdd" : {
                          "type" : "expression",
                          "value" : "{\r\n  \"persistenceId_string\" : \"\",\r\n  \"account_username\" : \"\",\r\n  \"account_password\" : \"\",\r\n  \"account_creationDate\" : null,\r\n  \"account_clientID\" : 0,\r\n  \"account_clientname\" : \"\"\r\n}"
                        },
                        "disabled" : {
                          "type" : "constant",
                          "value" : false
                        },
                        "alignment" : {
                          "type" : "constant",
                          "value" : "left"
                        },
                        "dimension" : {
                          "type" : "constant",
                          "value" : 12
                        }
                      },
                      "reference" : "4190d923-8c70-42bf-a316-59c73e0adf77",
                      "hasValidationError" : false,
                      "id" : "pbButton",
                      "description" : ""
                    }
                  ]
                ]
              }
            ],
            [
              {
                "type" : "component",
                "dimension" : {
                  "md" : 12,
                  "sm" : 12,
                  "xs" : 12,
                  "lg" : 12
                },
                "propertyValues" : {
                  "removeItem" : {
                    "type" : "variable"
                  },
                  "hidden" : {
                    "type" : "constant",
                    "value" : false
                  },
                  "cssClasses" : {
                    "type" : "constant",
                    "value" : ""
                  },
                  "buttonStyle" : {
                    "type" : "constant",
                    "value" : "primary"
                  },
                  "label" : {
                    "type" : "interpolation",
                    "value" : "Submit"
                  },
                  "dataToSend" : {
                    "type" : "expression",
                    "value" : "formOutput"
                  },
                  "dataFromError" : {
                    "type" : "variable",
                    "value" : "formOutput._submitError"
                  },
                  "allowHTML" : {
                    "type" : "constant",
                    "value" : false
                  },
                  "labelHidden" : {
                    "type" : "constant",
                    "value" : false
                  },
                  "collectionPosition" : {
                    "type" : "constant"
                  },
                  "targetUrlOnSuccess" : {
                    "type" : "interpolation",
                    "value" : "/bonita"
                  },
                  "action" : {
                    "type" : "constant",
                    "value" : "Submit task"
                  },
                  "collectionToModify" : {
                    "type" : "variable"
                  },
                  "valueToAdd" : {
                    "type" : "expression"
                  },
                  "disabled" : {
                    "type" : "expression",
                    "value" : "$form.$invalid"
                  },
                  "alignment" : {
                    "type" : "constant",
                    "value" : "center"
                  },
                  "dimension" : {
                    "type" : "constant",
                    "value" : 12
                  }
                },
                "reference" : "e7e6b7e2-8bc8-4251-97c6-743b05931701",
                "hasValidationError" : false,
                "id" : "pbButton",
                "description" : ""
              }
            ],
            [
              {
                "type" : "component",
                "dimension" : {
                  "md" : 12,
                  "sm" : 12,
                  "xs" : 12,
                  "lg" : 12
                },
                "propertyValues" : {
                  "allowHTML" : {
                    "type" : "constant",
                    "value" : true
                  },
                  "allowHtml" : {
                    "type" : "constant",
                    "value" : true
                  },
                  "labelHidden" : {
                    "type" : "constant",
                    "value" : true
                  },
                  "hidden" : {
                    "type" : "expression",
                    "value" : "!formOutput._submitError.message"
                  },
                  "cssClasses" : {
                    "type" : "constant",
                    "value" : "alert alert-danger col-lg-6 col-lg-offset-3"
                  },
                  "label" : {
                    "type" : "interpolation"
                  },
                  "text" : {
                    "type" : "interpolation",
                    "value" : "<strong>Debug message</strong>\n<br/>\n{{formOutput._submitError.message}}\n{{submit_errors_list}}"
                  },
                  "alignment" : {
                    "type" : "constant",
                    "value" : "left"
                  },
                  "dimension" : {
                    "type" : "constant",
                    "value" : 12
                  }
                },
                "reference" : "93e7f34c-9a57-4ddc-b662-51fdeb5ad874",
                "hasValidationError" : false,
                "id" : "pbText",
                "description" : ""
              }
            ]
          ]
        }
      }
    ]
  ],
  "variables" : {
    "slipstream_account_information" : {
      "type" : "url",
      "value" : [
        "{{slipstream|lazyRef:'account_information'}}"
      ],
      "exposed" : false
    },
    "task" : {
      "type" : "url",
      "value" : [
        "../API/bpm/userTask/{{taskId}}"
      ],
      "exposed" : false
    },
    "submit_errors_list" : {
      "type" : "expression",
      "value" : [
        "if($data.formOutput && $data.formOutput._submitError && $data.formOutput._submitError.explanations){",
        "\tconst liElements = $data.formOutput._submitError.explanations",
        "\t\t.filter(cause => cause !== null)",
        "\t\t.map(cause => \"<li>\" + cause + \"</li>\")",
        "\t\t.join('');",
        "\tif(liElements){",
        "\t\treturn \"<ul>\" + liElements + \"</ul>\";",
        "\t}",
        "}"
      ],
      "exposed" : false
    },
    "formOutput" : {
      "type" : "expression",
      "value" : [
        "if( $data.slipstream && $data.slipstream_account_information ){",
        "\t//attach lazy references variables to parent variables",
        "\t$data.slipstream.account_information = $data.slipstream_account_information;",
        "\treturn {",
        "\t\t//map slipstream variable to expected task contract input",
        "\t\tslipstreamInput: {",
        "\t\t\tclient_name: $data.slipstream.client_name !== undefined ? $data.slipstream.client_name : null,",
        "\t\t\tclient_ID: $data.slipstream.client_ID !== undefined ? $data.slipstream.client_ID : null,",
        "\t\t\thin_exist: $data.slipstream.hin_exist !== undefined ? $data.slipstream.hin_exist : null,",
        "\t\t\thin_number: $data.slipstream.hin_number !== undefined ? $data.slipstream.hin_number : null,",
        "\t\t\tdaily_transaction_limit: $data.slipstream.daily_transaction_limit !== undefined ? $data.slipstream.daily_transaction_limit : null,",
        "\t\t\tasset_transfer_requested: $data.slipstream.asset_transfer_requested !== undefined ? $data.slipstream.asset_transfer_requested : null,",
        "\t\t\tclient_existing_broker: $data.slipstream.client_existing_broker !== undefined ? $data.slipstream.client_existing_broker : null,",
        "\t\t\tcurrent_cash: $data.slipstream.current_cash !== undefined ? $data.slipstream.current_cash : null,",
        "\t\t\tbroker_ID: $data.slipstream.broker_ID !== undefined ? $data.slipstream.broker_ID : null,",
        "\t\t\ttrading_status: $data.slipstream.trading_status !== undefined ? $data.slipstream.trading_status : null,",
        "\t\t\taccount_information: $data.slipstream.account_information.map( it => ({",
        "\t\t\t\tpersistenceId_string: it.persistenceId_string !== undefined ? it.persistenceId_string : null",
        "\t\t\t}))",
        "\t\t}",
        "\t}",
        "}"
      ],
      "exposed" : false
    },
    "slipstream" : {
      "type" : "url",
      "value" : [
        "../{{context.slipstream_ref.link}}"
      ],
      "exposed" : false
    },
    "context" : {
      "type" : "url",
      "value" : [
        "../API/bpm/userTask/{{taskId}}/context"
      ],
      "exposed" : false
    },
    "accountInformation_query" : {
      "type" : "url",
      "value" : [
        "../API/bdm/businessData/com.company.model.AccountInformation?q=find&p=0&c=99"
      ],
      "exposed" : false
    },
    "taskId" : {
      "type" : "urlparameter",
      "value" : [
        "id"
      ],
      "exposed" : false
    }
  },
  "assets" : [
    {
      "id" : "bb65f09b-333a-4251-a98e-d2a68cc3189d",
      "name" : "localization.json",
      "type" : "json",
      "order" : 0,
      "external" : false
    },
    {
      "id" : "e3bdbbe8-7cb3-415c-b523-81e2dc2bff30",
      "name" : "style.css",
      "type" : "css",
      "order" : 0,
      "external" : false
    }
  ],
  "inactiveAssets" : [ ],
  "webResources" : [ ],
  "hasValidationError" : false
}